drawio/__init__.py
drawio/__main__.py
drawio/base.py
drawio/cli.py
drawio/controllers/__init__.py
drawio/entities/__init__.py
drawio/entities/config.py
drawio/entities/drawio.py
drawio/entities/drawio_app.py
drawio/entities/drawio_browser.py
drawio/entities/drawio_config/__init__.py
drawio/entities/drawio_config/abstract_config.py
drawio/entities/drawio_config/connect_config.py
drawio/entities/drawio_config/drawio_config.py
drawio/entities/erd/__init__.py
drawio/entities/erd/column.py
drawio/entities/erd/erd.py
drawio/entities/erd/table.py
drawio/entities/graph/__init__.py
drawio/entities/graph/edge.py
drawio/entities/graph/graph.py
drawio/entities/graph/node.py
drawio_python-0.1.0.dist-info/LICENSE
drawio_python-0.1.0.dist-info/METADATA
drawio_python-0.1.0.dist-info/WHEEL
drawio_python-0.1.0.dist-info/entry_points.txt
drawio_python-0.1.0.dist-info/top_level.txt
drawio_python-0.1.0.dist-info/RECORD
