Metadata-Version: 2.1
Name: drawio-python
Version: 0.1.0
Summary: Awesome drawio created by Nguyen Anh Binh
Home-page: https://github.com/maycuatroi/drawio/
Author: Nguyen Anh Binh
License-File: LICENSE
Provides-Extra: test
Requires-Dist: pytest ; extra == 'test'
Requires-Dist: coverage ; extra == 'test'
Requires-Dist: flake8 ; extra == 'test'
Requires-Dist: black ; extra == 'test'
Requires-Dist: isort ; extra == 'test'
Requires-Dist: pytest-cov ; extra == 'test'
Requires-Dist: codecov ; extra == 'test'
Requires-Dist: mypy ; extra == 'test'
Requires-Dist: gitchangelog ; extra == 'test'
Requires-Dist: mkdocs ; extra == 'test'
